Workbook

Sheet 🏠 Inicio
B1: Calculadora RM para avicultores
A2: Haz en segundos las cuentas de tu galpón de gallinas ponedoras | C2: ="Granja: "&'🏠 Inicio'!B6&" · Moneda: "&'🏠 Inicio'!B8 -> Granja: Mi granja · Moneda: COP $
A4: 1️⃣ Escribe en las celdas crema · 2️⃣ Mira los resultados en gris · 3️⃣ Revisa el Panel
A5: ✏️ PERSONALIZA TU GRANJA
A6: Nombre de tu granja | B6: Mi granja
A7: Tu nombre
A8: Moneda | B8: COP $
A9: Hojas de la calculadora
A10: 📈 Panel | B10: Tablero de indicadores y diagnóstico
A11: 🥚 Producción | B11: Postura, huevos y cubetas
A12: 🌽 Alimento | B12: Consumo, conversión y costos del alimento
A13: 💰 Costos y ganancia | B13: Ingresos, costos y punto de equilibrio
A14: 🔮 Simulador | B14: Sensibilidad de precios y postura
A15: 🐣 Levante | B15: Costo de crianza de pollitas
A16: 📐 Espacio y equipos | B16: Capacidad y equipos del galpón
A17: 💧 Agua | B17: Consumo y reserva de agua
A18: 💊 Medicamento en agua | B18: Dosis de producto en agua
A19: ⚖️ Mezcla de alimento | B19: Mezclas de ingredientes
A20: 💡 Luz | B20: Luz artificial y costo
A21: 📉 Mortalidad | B21: Mortalidad y viabilidad
... A26: 🐔 Gallina de descarte | B26: Ingreso por gallinas de descarte
A28: Los valores de referencia son orientativos. Ajústalos a la guía de tu línea genética y consulta a tu veterinario para vacunas y medicamentos.
A29: Versión v1 · octubre 2026

Sheet 📈 Panel
B1: Panel de tu granja | D1: ⟵ Volver al inicio
A2: Mira indicadores clave y recomendaciones orientativas. | C2: ="Granja: "&'🏠 Inicio'!B6&" · Moneda: "&'🏠 Inicio'!B8 -> Granja: Mi granja · Moneda: COP $
A4: TUS INDICADORES
A5: Postura | C5: =REPT("█",ROUND('🥚 Producción'!B10*20,0)) -> █████████████████
A6: ='🥚 Producción'!B10 -> 0.87
A8: Conversión kg alimento/kg huevo
A9: ='🌽 Alimento'!B18 -> 2.1319985
A11: Costo por huevo
A12: ='💰 Costos y ganancia'!B21 -> 428.28987
A14: Costo por cubeta
A15: ='💰 Costos y ganancia'!B22 -> 12848.696
A17: Ganancia del mes
A18: ='💰 Costos y ganancia'!B20 -> 1773750
A20: Precio mínimo de la cubeta
A21: ='💰 Costos y ganancia'!B23 -> 12848.696
A23: Costo por pollita lista
A24: ='🐣 Levante'!B18 -> 23562.5
A26: Mortalidad acumulada
A27: ='📉 Mortalidad'!B10 -> 0.045
A29: Huevos del ciclo
A30: ='📅 Proyección del lote'!B14 -> 334656
A33: 🧠 DIAGNÓSTICO RM
A34: =IF('🥚 Producción'!B10<0.8,"Tu postura está baja. Revisa horas de luz (16 h), consumo de alimento y agua, calor en el galpón y la edad del lote.",IF('🥚 Producción'!B10<0.9,"Postura aceptable; compárala semana a semana con la guía de tu línea.","¡Excelente postura! Mantén constantes la luz, el alimento y el agua.")) -> Postura aceptable; compárala semana a semana con la guía de tu línea.
A35: =IF('🌽 Alimento'!B18>2.4,"Estás gastando mucho alimento por kilo de huevo. Revisa desperdicio en comederos, roedores y el peso del huevo.","Conversión dentro de lo esperado.") -> Conversión dentro de lo esperado.
A36: =IF('💰 Costos y ganancia'!B20<=0,"Con estos números pierdes dinero: sube el precio de la cubeta al menos a "&FIXED('💰 Costos y ganancia'!B23,0)&" o baja costos.","Ganas "&FIXED('💰 Costos y ganancia'!B20,0)&" al mes, "&FIXED('💰 Costos y ganancia'!B25,0)&" por gallina.") -> Ganas 1773750 al mes, 1774 por gallina.
A37: =IF('📉 Mortalidad'!B10>0.08,"Mortalidad alta: revisa bioseguridad, vacunación con tu veterinario y calor.","Mortalidad bajo control.") -> Mortalidad bajo control.
A38: =IF('💡 Luz'!B11>0,"Necesitas "&FIXED('💡 Luz'!B11,1)&" h de luz artificial al día; cuesta "&FIXED('💡 Luz'!B14,0)&" al mes.","No necesitas luz artificial adicional.") -> Necesitas 4 h de luz artificial al día; cuesta 9720 al mes.
A39: =IF(LEFT('📐 Espacio y equipos'!B18,2)="No","Tu galpón no alcanza: "&'📐 Espacio y equipos'!B18&" m² o reduce el lote.","Espacio suficiente.") -> Espacio suficiente.
A40: ="Compara con la guía de "&'🐣 Levante'!B12&"." -> Compara con la guía de Babcock Brown.
A41: Diagnóstico orientativo con referencias generales. Para salud y vacunas, consulta a tu veterinario.
A43: Referencias generales; compáralas con la guía de tu línea.
A45: Calculadora RM · RM Agroinversiones · Cursos online de gallinas ponedoras · WhatsApp +57 322 952 1224

Sheet 🥚 Producción
B1: Producción | D1: ⟵ Volver al inicio
A2: Calcula postura, cubetas y masa de huevo. | C2: ="Granja: "&'🏠 Inicio'!B6&" · Moneda: "&'🏠 Inicio'!B8 -> Granja: Mi granja · Moneda: COP $
A4: ✏️ TUS DATOS
A5: Gallinas vivas hoy | B5: 1000 | C5: gallinas
A6: Huevos recogidos hoy | B6: 870 | C6: huevos
A7: Huevos por cubeta | B7: 30 | C7: huevos
A8: Peso promedio del huevo en gramos | B8: 62 | C8: g
A9: 📊 RESULTADOS
A10: % de postura | B10: =IF(B5=0,0,B6/B5) -> 0.87
A11: Cubetas del día | B11: =IF(B7=0,0,QUOTIENT(B6,B7)) -> 29 | C11: cubetas
A12: Huevos sueltos (sobrantes) | B12: =IF(B7=0,0,MOD(B6,B7)) -> 0 | C12: huevos
A13: Masa de huevo del día en kg | B13: =B6*B8/1000 -> 53.94 | C13: kg
A14: Huevos al mes (30 días) | B14: =B6*30 -> 26100 | C14: huevos
A15: Cubetas al mes | B15: =IF(B7=0,0,B6*30/B7) -> 870 | C15: cubetas
A17: Calculadora RM · RM Agroinversiones · Cursos online de gallinas ponedoras · WhatsApp +57 322 952 1224

Sheet 🌽 Alimento
B1: Alimento | D1: ⟵ Volver al inicio
A2: Calcula consumo, conversión y costo del alimento. | C2: ="Granja: "&'🏠 Inicio'!B6&" · Moneda: "&'🏠 Inicio'!B8 -> Granja: Mi granja · Moneda: COP $
A4: ✏️ TUS DATOS
A5: Gallinas | B5: 1000 | C5: gallinas
A6: Consumo por gallina al día en gramos | B6: 115 | C6: Referencia: ajústalo a la guía de tu línea genética
A7: Kilos por bulto | B7: 40 | C7: kg
A8: Precio del bulto | B8: 95000 | C8: ='🏠 Inicio'!B8 -> COP $
A9: Huevos al día | B9: 870 | C9: huevos
A10: Peso promedio del huevo en g | B10: 62 | C10: g
A11: 📊 RESULTADOS
A12: Kg de alimento al día | B12: =B5*B6/1000 -> 115 | C12: kg
A13: Bultos al día | B13: =IF(B7=0,0,B12/B7) -> 2.875 | C13: bultos
A14: Bultos a la semana | B14: =B13*7 -> 20.125 | C14: bultos
A15: Bultos al mes (30 días) | B15: =B13*30 -> 86.25 | C15: bultos
A16: Costo del alimento al día | B16: =IF(B7=0,0,B13*B8) -> 273125 | C16: ='🏠 Inicio'!B8 -> COP $
A17: Costo del alimento al mes | B17: =B16*30 -> 8193750 | C17: ='🏠 Inicio'!B8 -> COP $
A18: Conversión: kg alimento por kg huevo | B18: =IF(B9*B10/1000=0,0,B12/(B9*B10/1000)) -> 2.1319985 | C18: kg/kg
A19: Kg de alimento por docena | B19: =IF(B9=0,0,B12/(B9/12)) -> 1.5862069 | C19: kg
A20: Costo de alimento por huevo | B20: =IF(B9=0,0,B16/B9) -> 313.93678 | C20: ='🏠 Inicio'!B8 -> COP $
A22: Calculadora RM · RM Agroinversiones · Cursos online de gallinas ponedoras · WhatsApp +57 322 952 1224

Sheet 💰 Costos y ganancia
B1: Costos y ganancia | D1: ⟵ Volver al inicio
A2: Estima ingresos, costos y punto de equilibrio. | C2: ="Granja: "&'🏠 Inicio'!B6&" · Moneda: "&'🏠 Inicio'!B8 -> Granja: Mi granja · Moneda: COP $
A4: ✏️ TUS DATOS
A5: Gallinas | B5: 1000 | C5: gallinas
A6: % de postura promedio | B6: 0.85
A7: Precio de venta por cubeta de 30 | B7: 15000 | C7: ='🏠 Inicio'!B8 -> COP $
A8: Huevos por cubeta | B8: 30 | C8: huevos
A9: Costo del alimento al mes | B9: ='🌽 Alimento'!B17 -> 8193750 | C9: Puedes copiarlo de la hoja Alimento
A10: Mano de obra al mes | B10: 1500000 | C10: ='🏠 Inicio'!B8 -> COP $
A11: Vacunas, vitaminas y sanidad al mes | B11: 300000 | C11: ='🏠 Inicio'!B8 -> COP $
A12: Energía, agua y transporte al mes | B12: 400000 | C12: ='🏠 Inicio'!B8 -> COP $
A13: Otros costos al mes | B13: 200000 | C13: ='🏠 Inicio'!B8 -> COP $
A14: Pérdida por huevos rotos o de descarte | B14: 0.03
A15: 📊 RESULTADOS
A16: Huevos vendibles al mes | B16: =B5*B6*30*(1-B14) -> 24735 | C16: huevos
A17: Cubetas vendibles al mes | B17: =IF(B8=0,0,B16/B8) -> 824.5 | C17: cubetas
A18: Ingresos al mes | B18: =B17*B7 -> 12367500 | C18: ='🏠 Inicio'!B8 -> COP $
A19: Costos totales al mes | B19: =SUM(B9:B13) -> 10593750 | C19: ='🏠 Inicio'!B8 -> COP $
A20: Ganancia (o pérdida) al mes | B20: =B18-B19 -> 1773750 | C20: ='🏠 Inicio'!B8 -> COP $
A21: Costo por huevo | B21: =IF(B16=0,0,B19/B16) -> 428.28987 | C21: ='🏠 Inicio'!B8 -> COP $
A22: Costo por cubeta | B22: =IF(B17=0,0,B19/B17) -> 12848.696 | C22: ='🏠 Inicio'!B8 -> COP $
A23: Precio mínimo de la cubeta para no perder | B23: =B22 -> 12848.696 | C23: ='🏠 Inicio'!B8 -> COP $
A24: Margen por cubeta | B24: =B7-B23 -> 2151.3038 | C24: ='🏠 Inicio'!B8 -> COP $
A25: Ganancia por gallina al mes | B25: =IF(B5=0,0,B20/B5) -> 1773.75 | C25: ='🏠 Inicio'!B8 -> COP $
A26: % de postura mínimo para no perder | B26: =IF(B5*30*(1-B14)*B7/B8=0,0,B19/(B5*30*(1-B14)*B7/B8)) -> 0.72809278
A28: Calculadora RM · RM Agroinversiones · Cursos online de gallinas ponedoras · WhatsApp +57 322 952 1224

Sheet 🔮 Simulador
B1: 🔮 ¿Qué pasa si…? | D1: ⟵ Volver al inicio
A2: Explora cómo cambian tus ganancias al variar precios y postura. | C2: ="Granja: "&'🏠 Inicio'!B6&" · Moneda: "&'🏠 Inicio'!B8 -> Granja: Mi granja · Moneda: COP $
A4: GANANCIA DEL MES · ALIMENTO / CUBETA
A5: Bulto ↓ / Cubeta → | B5: ='💰 Costos y ganancia'!B7*0.8 -> 12000 | C5: ='💰 Costos y ganancia'!B7*0.9 -> 13500 | D5: ='💰 Costos y ganancia'!B7*1 -> 15000 | E5: ='💰 Costos y ganancia'!B7*1.1 -> 16500 | F5: ='💰 Costos y ganancia'!B7*1.2 -> 18000
A6: ='🌽 Alimento'!B8*0.8 -> 76000 | B6: ='💰 Costos y ganancia'!B5*'💰 Costos y ganancia'!B6*30*(1-'💰 Costos y ganancia'!B14)/'💰 Costos y ganancia'!B8*(B$5)-('💰 Costos y ganancia'!B10+'💰 Costos y ganancia'!B11+'💰 Costos y ganancia'!B12+'💰 Costos y ganancia'!B13+'🌽 Alimento'!B17*($A6/'🌽 Alimento'!B8)) -> 939000 | C6: ='💰 Costos y ganancia'!B5*'💰 Costos y ganancia'!B6*30*(1-'💰 Costos y ganancia'!B14)/'💰 Costos y ganancia'!B8*(C$5)-('💰 Costos y ganancia'!B10+'💰 Costos y ganancia'!B11+'💰 Costos y ganancia'!B12+'💰 Costos y ganancia'!B13+'🌽 Alimento'!B17*($A6/'🌽 Alimento'!B8)) -> 2175750 | D6: ='💰 Costos y ganancia'!B5*'💰 Costos y ganancia'!B6*30*(1-'💰 Costos y ganancia'!B14)/'💰 Costos y ganancia'!B8*(D$5)-('💰 Costos y ganancia'!B10+'💰 Costos y ganancia'!B11+'💰 Costos y ganancia'!B12+'💰 Costos y ganancia'!B13+'🌽 Alimento'!B17*($A6/'🌽 Alimento'!B8)) -> 3412500 | E6: ='💰 Costos y ganancia'!B5*'💰 Costos y ganancia'!B6*30*(1-'💰 Costos y ganancia'!B14)/'💰 Costos y ganancia'!B8*(E$5)-('💰 Costos y ganancia'!B10+'💰 Costos y ganancia'!B11+'💰 Costos y ganancia'!B12+'💰 Costos y ganancia'!B13+'🌽 Alimento'!B17*($A6/'🌽 Alimento'!B8)) -> 4649250 | F6: ='💰 Costos y ganancia'!B5*'💰 Costos y ganancia'!B6*30*(1-'💰 Costos y ganancia'!B14)/'💰 Costos y ganancia'!B8*(F$5)-('💰 Costos y ganancia'!B10+'💰 Costos y ganancia'!B11+'💰 Costos y ganancia'!B12+'💰 Costos y ganancia'!B13+'🌽 Alimento'!B17*($A6/'🌽 Alimento'!B8)) -> 5886000
A7: ='🌽 Alimento'!B8*0.9 -> 85500 | B7: ='💰 Costos y ganancia'!B5*'💰 Costos y ganancia'!B6*30*(1-'💰 Costos y ganancia'!B14)/'💰 Costos y ganancia'!B8*(B$5)-('💰 Costos y ganancia'!B10+'💰 Costos y ganancia'!B11+'💰 Costos y ganancia'!B12+'💰 Costos y ganancia'!B13+'🌽 Alimento'!B17*($A7/'🌽 Alimento'!B8)) -> 119625 | C7: ='💰 Costos y ganancia'!B5*'💰 Costos y ganancia'!B6*30*(1-'💰 Costos y ganancia'!B14)/'💰 Costos y ganancia'!B8*(C$5)-('💰 Costos y ganancia'!B10+'💰 Costos y ganancia'!B11+'💰 Costos y ganancia'!B12+'💰 Costos y ganancia'!B13+'🌽 Alimento'!B17*($A7/'🌽 Alimento'!B8)) -> 1356375 | D7: ='💰 Costos y ganancia'!B5*'💰 Costos y ganancia'!B6*30*(1-'💰 Costos y ganancia'!B14)/'💰 Costos y ganancia'!B8*(D$5)-('💰 Costos y ganancia'!B10+'💰 Costos y ganancia'!B11+'💰 Costos y ganancia'!B12+'💰 Costos y ganancia'!B13+'🌽 Alimento'!B17*($A7/'🌽 Alimento'!B8)) -> 2593125 | E7: ='💰 Costos y ganancia'!B5*'💰 Costos y ganancia'!B6*30*(1-'💰 Costos y ganancia'!B14)/'💰 Costos y ganancia'!B8*(E$5)-('💰 Costos y ganancia'!B10+'💰 Costos y ganancia'!B11+'💰 Costos y ganancia'!B12+'💰 Costos y ganancia'!B13+'🌽 Alimento'!B17*($A7/'🌽 Alimento'!B8)) -> 3829875 | F7: ='💰 Costos y ganancia'!B5*'💰 Costos y ganancia'!B6*30*(1-'💰 Costos y ganancia'!B14)/'💰 Costos y ganancia'!B8*(F$5)-('💰 Costos y ganancia'!B10+'💰 Costos y ganancia'!B11+'💰 Costos y ganancia'!B12+'💰 Costos y ganancia'!B13+'🌽 Alimento'!B17*($A7/'🌽 Alimento'!B8)) -> 5066625
A8: ='🌽 Alimento'!B8*1 -> 95000 | B8: ='💰 Costos y ganancia'!B5*'💰 Costos y ganancia'!B6*30*(1-'💰 Costos y ganancia'!B14)/'💰 Costos y ganancia'!B8*(B$5)-('💰 Costos y ganancia'!B10+'💰 Costos y ganancia'!B11+'💰 Costos y ganancia'!B12+'💰 Costos y ganancia'!B13+'🌽 Alimento'!B17*($A8/'🌽 Alimento'!B8)) -> -699750 | C8: ='💰 Costos y ganancia'!B5*'💰 Costos y ganancia'!B6*30*(1-'💰 Costos y ganancia'!B14)/'💰 Costos y ganancia'!B8*(C$5)-('💰 Costos y ganancia'!B10+'💰 Costos y ganancia'!B11+'💰 Costos y ganancia'!B12+'💰 Costos y ganancia'!B13+'🌽 Alimento'!B17*($A8/'🌽 Alimento'!B8)) -> 537000 | D8: ='💰 Costos y ganancia'!B5*'💰 Costos y ganancia'!B6*30*(1-'💰 Costos y ganancia'!B14)/'💰 Costos y ganancia'!B8*(D$5)-('💰 Costos y ganancia'!B10+'💰 Costos y ganancia'!B11+'💰 Costos y ganancia'!B12+'💰 Costos y ganancia'!B13+'🌽 Alimento'!B17*($A8/'🌽 Alimento'!B8)) -> 1773750 | E8: ='💰 Costos y ganancia'!B5*'💰 Costos y ganancia'!B6*30*(1-'💰 Costos y ganancia'!B14)/'💰 Costos y ganancia'!B8*(E$5)-('💰 Costos y ganancia'!B10+'💰 Costos y ganancia'!B11+'💰 Costos y ganancia'!B12+'💰 Costos y ganancia'!B13+'🌽 Alimento'!B17*($A8/'🌽 Alimento'!B8)) -> 3010500 | F8: ='💰 Costos y ganancia'!B5*'💰 Costos y ganancia'!B6*30*(1-'💰 Costos y ganancia'!B14)/'💰 Costos y ganancia'!B8*(F$5)-('💰 Costos y ganancia'!B10+'💰 Costos y ganancia'!B11+'💰 Costos y ganancia'!B12+'💰 Costos y ganancia'!B13+'🌽 Alimento'!B17*($A8/'🌽 Alimento'!B8)) -> 4247250
A9: ='🌽 Alimento'!B8*1.1 -> 104500 | B9: ='💰 Costos y ganancia'!B5*'💰 Costos y ganancia'!B6*30*(1-'💰 Costos y ganancia'!B14)/'💰 Costos y ganancia'!B8*(B$5)-('💰 Costos y ganancia'!B10+'💰 Costos y ganancia'!B11+'💰 Costos y ganancia'!B12+'💰 Costos y ganancia'!B13+'🌽 Alimento'!B17*($A9/'🌽 Alimento'!B8)) -> -1519125 | C9: ='💰 Costos y ganancia'!B5*'💰 Costos y ganancia'!B6*30*(1-'💰 Costos y ganancia'!B14)/'💰 Costos y ganancia'!B8*(C$5)-('💰 Costos y ganancia'!B10+'💰 Costos y ganancia'!B11+'💰 Costos y ganancia'!B12+'💰 Costos y ganancia'!B13+'🌽 Alimento'!B17*($A9/'🌽 Alimento'!B8)) -> -282375 | D9: ='💰 Costos y ganancia'!B5*'💰 Costos y ganancia'!B6*30*(1-'💰 Costos y ganancia'!B14)/'💰 Costos y ganancia'!B8*(D$5)-('💰 Costos y ganancia'!B10+'💰 Costos y ganancia'!B11+'💰 Costos y ganancia'!B12+'💰 Costos y ganancia'!B13+'🌽 Alimento'!B17*($A9/'🌽 Alimento'!B8)) -> 954375 | E9: ='💰 Costos y ganancia'!B5*'💰 Costos y ganancia'!B6*30*(1-'💰 Costos y ganancia'!B14)/'💰 Costos y ganancia'!B8*(E$5)-('💰 Costos y ganancia'!B10+'💰 Costos y ganancia'!B11+'💰 Costos y ganancia'!B12+'💰 Costos y ganancia'!B13+'🌽 Alimento'!B17*($A9/'🌽 Alimento'!B8)) -> 2191125 | F9: ='💰 Costos y ganancia'!B5*'💰 Costos y ganancia'!B6*30*(1-'💰 Costos y ganancia'!B14)/'💰 Costos y ganancia'!B8*(F$5)-('💰 Costos y ganancia'!B10+'💰 Costos y ganancia'!B11+'💰 Costos y ganancia'!B12+'💰 Costos y ganancia'!B13+'🌽 Alimento'!B17*($A9/'🌽 Alimento'!B8)) -> 3427875
A10: ='🌽 Alimento'!B8*1.2 -> 114000 | B10: ='💰 Costos y ganancia'!B5*'💰 Costos y ganancia'!B6*30*(1-'💰 Costos y ganancia'!B14)/'💰 Costos y ganancia'!B8*(B$5)-('💰 Costos y ganancia'!B10+'💰 Costos y ganancia'!B11+'💰 Costos y ganancia'!B12+'💰 Costos y ganancia'!B13+'🌽 Alimento'!B17*($A10/'🌽 Alimento'!B8)) -> -2338500 | C10: ='💰 Costos y ganancia'!B5*'💰 Costos y ganancia'!B6*30*(1-'💰 Costos y ganancia'!B14)/'💰 Costos y ganancia'!B8*(C$5)-('💰 Costos y ganancia'!B10+'💰 Costos y ganancia'!B11+'💰 Costos y ganancia'!B12+'💰 Costos y ganancia'!B13+'🌽 Alimento'!B17*($A10/'🌽 Alimento'!B8)) -> -1101750 | D10: ='💰 Costos y ganancia'!B5*'💰 Costos y ganancia'!B6*30*(1-'💰 Costos y ganancia'!B14)/'💰 Costos y ganancia'!B8*(D$5)-('💰 Costos y ganancia'!B10+'💰 Costos y ganancia'!B11+'💰 Costos y ganancia'!B12+'💰 Costos y ganancia'!B13+'🌽 Alimento'!B17*($A10/'🌽 Alimento'!B8)) -> 135000 | E10: ='💰 Costos y ganancia'!B5*'💰 Costos y ganancia'!B6*30*(1-'💰 Costos y ganancia'!B14)/'💰 Costos y ganancia'!B8*(E$5)-('💰 Costos y ganancia'!B10+'💰 Costos y ganancia'!B11+'💰 Costos y ganancia'!B12+'💰 Costos y ganancia'!B13+'🌽 Alimento'!B17*($A10/'🌽 Alimento'!B8)) -> 1371750 | F10: ='💰 Costos y ganancia'!B5*'💰 Costos y ganancia'!B6*30*(1-'💰 Costos y ganancia'!B14)/'💰 Costos y ganancia'!B8*(F$5)-('💰 Costos y ganancia'!B10+'💰 Costos y ganancia'!B11+'💰 Costos y ganancia'!B12+'💰 Costos y ganancia'!B13+'🌽 Alimento'!B17*($A10/'🌽 Alimento'!B8)) -> 2608500
A13: % postura
A14: 0.7 | B14: ='💰 Costos y ganancia'!B5*A14*30*(1-'💰 Costos y ganancia'!B14)/'💰 Costos y ganancia'!B8*'💰 Costos y ganancia'!B7-'💰 Costos y ganancia'!B19 -> -408750
A15: 0.75 | B15: ='💰 Costos y ganancia'!B5*A15*30*(1-'💰 Costos y ganancia'!B14)/'💰 Costos y ganancia'!B8*'💰 Costos y ganancia'!B7-'💰 Costos y ganancia'!B19 -> 318750
A16: 0.8 | B16: ='💰 Costos y ganancia'!B5*A16*30*(1-'💰 Costos y ganancia'!B14)/'💰 Costos y ganancia'!B8*'💰 Costos y ganancia'!B7-'💰 Costos y ganancia'!B19 -> 1046250
A17: 0.85 | B17: ='💰 Costos y ganancia'!B5*A17*30*(1-'💰 Costos y ganancia'!B14)/'💰 Costos y ganancia'!B8*'💰 Costos y ganancia'!B7-'💰 Costos y ganancia'!B19 -> 1773750
A18: 0.9 | B18: ='💰 Costos y ganancia'!B5*A18*30*(1-'💰 Costos y ganancia'!B14)/'💰 Costos y ganancia'!B8*'💰 Costos y ganancia'!B7-'💰 Costos y ganancia'!B19 -> 2501250
A19: 0.95 | B19: ='💰 Costos y ganancia'!B5*A19*30*(1-'💰 Costos y ganancia'!B14)/'💰 Costos y ganancia'!B8*'💰 Costos y ganancia'!B7-'💰 Costos y ganancia'!B19 -> 3228750
A22: Calculadora RM · RM Agroinversiones · Cursos online de gallinas ponedoras · WhatsApp +57 322 952 1224

Sheet 🐣 Levante
B1: Levante (pollita) | D1: ⟵ Volver al inicio
A2: Calcula el costo de criar pollitas hasta postura. | C2: ="Granja: "&'🏠 Inicio'!B6&" · Moneda: "&'🏠 Inicio'!B8 -> Granja: Mi granja · Moneda: COP $
A4: ✏️ TUS DATOS
A5: Número de pollitas | B5: 1000 | C5: pollitas
A6: Precio de la pollita de un día | B6: 4500 | C6: ='🏠 Inicio'!B8 -> COP $
A7: Alimento acumulado por pollita hasta la semana de traslado en kg | B7: 6.2 | C7: Referencia: ajústalo a la guía de tu línea genética
A8: Precio del kilo de alimento de levante | B8: 2600 | C8: ='🏠 Inicio'!B8 -> COP $
A9: Vacunas y sanidad por pollita | B9: 1200 | C9: ='🏠 Inicio'!B8 -> COP $
A10: Otros costos por pollita | B10: 800 | C10: ='🏠 Inicio'!B8 -> COP $
A11: Mortalidad esperada en el levante | B11: 0.04
A12: Línea genética | B12: Babcock Brown
A13: 📊 RESULTADOS
A14: Pollitas que llegan a postura | B14: =B5*(1-B11) -> 960 | C14: pollitas
A15: Alimento total del levante en kg | B15: =B5*B7 -> 6200 | C15: kg
A16: Bultos de 40 kg | B16: =B15/40 -> 155 | C16: bultos
A17: Costo total del levante | B17: =B5*(B6+B7*B8+B9+B10) -> 22620000 | C17: ='🏠 Inicio'!B8 -> COP $
A18: Costo por pollita lista | B18: =IF(B14=0,0,B17/B14) -> 23562.5 | C18: ='🏠 Inicio'!B8 -> COP $
A20: Calculadora RM · RM Agroinversiones · Cursos online de gallinas ponedoras · WhatsApp +57 322 952 1224

Sheet 📐 Espacio y equipos
B1: Espacio y equipos | D1: ⟵ Volver al inicio
A2: Calcula capacidad y equipos para tu galpón. | C2: ="Granja: "&'🏠 Inicio'!B6&" · Moneda: "&'🏠 Inicio'!B8 -> Granja: Mi granja · Moneda: COP $
A4: ✏️ TUS DATOS
A5: Largo del galpón en metros | B5: 20 | C5: m
A6: Ancho en metros | B6: 8 | C6: m
A7: Aves por metro cuadrado en piso | B7: 6 | C7: Referencia: ajústalo a la guía de tu línea genética
A8: Gallinas a alojar | B8: 1000 | C8: gallinas
A9: Cm de comedero lineal por gallina | B9: 10 | C9: Referencia: ajústalo a la guía de tu línea genética
A10: Gallinas por comedero de tolva | B10: 25 | C10: Referencia: ajústalo a la guía de tu línea genética
A11: Gallinas por niple | B11: 10 | C11: Referencia: ajústalo a la guía de tu línea genética
A12: Gallinas por bebedero de campana | B12: 100 | C12: Referencia: ajústalo a la guía de tu línea genética
A13: Gallinas por nido | B13: 5 | C13: Referencia: ajústalo a la guía de tu línea genética
A14: Sistema | B14: Piso
A15: Centímetros cuadrados por gallina en jaula | B15: 500 | C15: Referencia: ajústalo a la guía de tu línea genética
A16: 📊 RESULTADOS
A17: Área en m² | B17: =B5*B6 -> 160 | C17: m²
A18: Capacidad máxima en piso (gallinas) | B18: =IF(B14="Jaula",IF(B15=0,0,B17*10000/B15),B17*B7) -> 960 | C18: gallinas
A19: ¿Cabe el lote? | B19: =IF(B8<=B18,"Sí, sobra espacio para "&ROUND(B18-B8,0)&" gallinas","No, te faltan "&ROUND((B8-B18)/IF(B14="Jaula",10000/B15,B7),1)&" m²") -> No, te faltan 6.7 m²
A20: Metros de comedero lineal | B20: =B8*B9/100 -> 100 | C20: m
A21: Comederos de tolva | B21: =IF(B10=0,0,ROUNDUP(B8/B10,0)) -> 40 | C21: unidades
A22: Niples | B22: =IF(B11=0,0,ROUNDUP(B8/B11,0)) -> 100 | C22: unidades
A23: Bebederos de campana | B23: =IF(B12=0,0,ROUNDUP(B8/B12,0)) -> 10 | C23: unidades
A24: Nidos | B24: =IF(B13=0,0,ROUNDUP(B8/B13,0)) -> 200 | C24: unidades
A26: Calculadora RM · RM Agroinversiones · Cursos online de gallinas ponedoras · WhatsApp +57 322 952 1224

Sheet 💧 Agua
B1: Agua | D1: ⟵ Volver al inicio
A2: Estima el consumo y la reserva de agua. | C2: ="Granja: "&'🏠 Inicio'!B6&" · Moneda: "&'🏠 Inicio'!B8 -> Granja: Mi granja · Moneda: COP $
A4: ✏️ TUS DATOS
A5: Gallinas | B5: ='🌽 Alimento'!B5 -> 1000 | C5: gallinas
A6: Consumo de alimento por gallina en g | B6: ='🌽 Alimento'!B6 -> 115 | C6: g
A7: Litros de agua por kg de alimento | B7: 2 | C7: Referencia: con calor sube a 3 o más
A8: Días de reserva que quieres en el tanque | B8: 2 | C8: días
A9: 📊 RESULTADOS
A10: Litros de agua al día | B10: =B5*B6/1000*B7 -> 230 | C10: L
A11: Litros por gallina al día | B11: =IF(B5=0,0,B10/B5) -> 0.23 | C11: L
A12: Tamaño mínimo del tanque en litros | B12: =B10*B8 -> 460 | C12: L
A14: Calculadora RM · RM Agroinversiones · Cursos online de gallinas ponedoras · WhatsApp +57 322 952 1224

Sheet 💊 Medicamento en agua
B1: Medicamento en agua | D1: ⟵ Volver al inicio
A2: Calcula el producto según la etiqueta o indicación veterinaria. | C2: ="Granja: "&'🏠 Inicio'!B6&" · Moneda: "&'🏠 Inicio'!B8 -> Granja: Mi granja · Moneda: COP $
A4: ✏️ TUS DATOS
A5: Litros de agua que toman al día | B5: ='💧 Agua'!B10 -> 230 | C5: L
A6: Dosis de la etiqueta en ml o g por litro | B6: 1 | C6: ml o g/L
A7: Días de tratamiento | B7: 5 | C7: días
A8: Contenido del frasco o sobre en ml o g | B8: 500 | C8: ml o g
A9: 📊 RESULTADOS
A10: Producto por día | B10: =B5*B6 -> 230 | C10: ml o g
A11: Producto para todo el tratamiento | B11: =B10*B7 -> 1150 | C11: ml o g
A12: Frascos o sobres necesarios | B12: =IF(B8=0,0,ROUNDUP(B11/B8,0)) -> 3 | C12: unidades
A13: DOSIS POR PESO
A14: Dosis en mg por kg de peso | B14: 10 | C14: mg/kg
A15: Peso promedio de la gallina en kg | B15: 1.9 | C15: kg
A16: Gallinas | B16: 1000 | C16: gallinas
A17: Concentración del producto en mg por ml o g | B17: 100 | C17: mg/ml o g
A18: RESULTADOS POR PESO
A19: mg al día para el lote | B19: =B14*B15*B16 -> 19000 | C19: mg
A20: ml o g de producto al día | B20: =IF(B17=0,0,B19/B17) -> 190 | C20: ml o g
A21: ml o g por litro de agua | B21: =IF(B5=0,0,B20/B5) -> 0.82608696 | C21: ml o g/L
A23: Calculadora RM · RM Agroinversiones · Cursos online de gallinas ponedoras · WhatsApp +57 322 952 1224

Sheet ⚖️ Mezcla de alimento
B1: Mezcla (cuadrado de Pearson) | D1: ⟵ Volver al inicio
A2: Calcula una mezcla aproximada de dos ingredientes. | C2: ="Granja: "&'🏠 Inicio'!B6&" · Moneda: "&'🏠 Inicio'!B8 -> Granja: Mi granja · Moneda: COP $
A4: ✏️ TUS DATOS
A5: Proteína del ingrediente A en % | B5: 8.5 | C5: ej. maíz
A6: Proteína del ingrediente B en % | B6: 46 | C6: ej. torta de soya
A7: Proteína que quieres en la mezcla en % | B7: 17 | C7: %
A8: Kg de mezcla a preparar | B8: 100 | C8: kg
A9: 📊 RESULTADOS
A10: Partes de A | B10: =ABS(B6-B7) -> 29 | C10: partes
A11: Partes de B | B11: =ABS(B5-B7) -> 8.5 | C11: partes
A12: % de A | B12: =IF(B10+B11=0,0,B10/(B10+B11)) -> 0.77333333
A13: % de B | B13: =IF(B10+B11=0,0,B11/(B10+B11)) -> 0.22666667
A14: Kg de A | B14: =B12*B8 -> 77.333333 | C14: kg
A15: Kg de B | B15: =B13*B8 -> 22.666667 | C15: kg
A16: Validación | B16: =IF(OR(B7<MIN(B5,B6),B7>MAX(B5,B6)),"El objetivo debe estar entre la proteína de A y la de B","Mezcla válida") -> Mezcla válida
A18: Calculadora RM · RM Agroinversiones · Cursos online de gallinas ponedoras · WhatsApp +57 322 952 1224

Sheet 💡 Luz
B1: Luz | D1: ⟵ Volver al inicio
A2: Calcula horas de luz artificial y su costo. | C2: ="Granja: "&'🏠 Inicio'!B6&" · Moneda: "&'🏠 Inicio'!B8 -> Granja: Mi granja · Moneda: COP $
A4: ✏️ TUS DATOS
A5: Horas de luz total que quieres | B5: 16 | C5: Referencia para postura
A6: Horas de luz natural del día | B6: 12 | C6: horas
A7: Bombillos | B7: 10 | C7: unidades
A8: Vatios por bombillo | B8: 9 | C8: W
A9: Precio del kWh | B9: 900 | C9: ='🏠 Inicio'!B8 -> COP $
A10: 📊 RESULTADOS
A11: Horas de luz artificial al día | B11: =MAX(0,B5-B6) -> 4 | C11: h
A12: kWh al día | B12: =B7*B8*B11/1000 -> 0.36 | C12: kWh
A13: Costo de luz al día | B13: =B12*B9 -> 324 | C13: ='🏠 Inicio'!B8 -> COP $
A14: Costo al mes | B14: =B13*30 -> 9720 | C14: ='🏠 Inicio'!B8 -> COP $
A16: Calculadora RM · RM Agroinversiones · Cursos online de gallinas ponedoras · WhatsApp +57 322 952 1224

Sheet 📉 Mortalidad
B1: Mortalidad | D1: ⟵ Volver al inicio
A2: Controla mortalidad semanal y acumulada. | C2: ="Granja: "&'🏠 Inicio'!B6&" · Moneda: "&'🏠 Inicio'!B8 -> Granja: Mi granja · Moneda: COP $
A4: ✏️ TUS DATOS
A5: Gallinas al inicio | B5: 1000 | C5: gallinas
A6: Muertes de la semana | B6: 3 | C6: gallinas
A7: Muertes acumuladas del lote | B7: 45 | C7: gallinas
A8: 📊 RESULTADOS
A9: % mortalidad de la semana | B9: =IF(B5=0,0,B6/B5) -> 0.003
A10: % mortalidad acumulada | B10: =IF(B5=0,0,B7/B5) -> 0.045
A11: Gallinas vivas | B11: =MAX(0,B5-B7) -> 955 | C11: gallinas
A12: Viabilidad (%) | B12: =IF(B5=0,0,(B5-B7)/B5) -> 0.955
A14: Calculadora RM · RM Agroinversiones · Cursos online de gallinas ponedoras · WhatsApp +57 322 952 1224

Sheet 📅 Proyección del lote
B1: Proyección del lote | D1: ⟵ Volver al inicio
A2: Proyecta producción e ingresos de un ciclo. | C2: ="Granja: "&'🏠 Inicio'!B6&" · Moneda: "&'🏠 Inicio'!B8 -> Granja: Mi granja · Moneda: COP $
A4: ✏️ TUS DATOS
A5: Gallinas al iniciar postura | B5: 1000 | C5: gallinas
A6: Semanas de postura | B6: 60 | C6: semanas
A7: % de postura promedio del ciclo | B7: 0.83
A8: Mortalidad total esperada en el ciclo | B8: 0.08
A9: Precio por cubeta | B9: 15000 | C9: ='🏠 Inicio'!B8 -> COP $
A10: Huevos por cubeta | B10: 30 | C10: huevos
A11: Línea genética | B11: Babcock Brown
A12: 📊 RESULTADOS
A13: Gallinas promedio | B13: =B5*(1-B8/2) -> 960 | C13: gallinas
A14: Huevos totales del ciclo | B14: =B13*B6*7*B7 -> 334656 | C14: huevos
A15: Cubetas | B15: =IF(B10=0,0,B14/B10) -> 11155.2 | C15: cubetas
A16: Ingresos del ciclo | B16: =B15*B9 -> 167328000 | C16: ='🏠 Inicio'!B8 -> COP $
A17: Huevos por gallina inicial | B17: =IF(B5=0,0,B14/B5) -> 334.656 | C17: huevos
A19: Calculadora RM · RM Agroinversiones · Cursos online de gallinas ponedoras · WhatsApp +57 322 952 1224

Sheet 🔠 Clasificación del huevo
B1: Clasificación del huevo | D1: ⟵ Volver al inicio
A2: Clasifica por peso y estima proporciones e ingresos. | C2: ="Granja: "&'🏠 Inicio'!B6&" · Moneda: "&'🏠 Inicio'!B8 -> Granja: Mi granja · Moneda: COP $
A4: ✏️ TUS DATOS
A5: Categoría | B5: Huevos del día | C5: Precio por cubeta | D5: Rango de referencia | E5: % | F5: Ingreso del día
A6: Jumbo | B6: 20 | C6: 21000 | D6: ≥ 78 g | E6: =IF(SUM(B6:B11)=0,0,B6/SUM(B6:B11)) -> 0.022988506 | F6: =IF(B6=0,0,B6/30*C6) -> 14000
A7: AAA | B7: 180 | C7: 18000 | D7: 67 a 77,9 g | E7: =IF(SUM(B6:B11)=0,0,B7/SUM(B6:B11)) -> 0.20689655 | F7: =IF(B7=0,0,B7/30*C7) -> 108000
A8: AA | B8: 400 | C8: 16000 | D8: 60 a 66,9 g | E8: =IF(SUM(B6:B11)=0,0,B8/SUM(B6:B11)) -> 0.45977011 | F8: =IF(B8=0,0,B8/30*C8) -> 213333.33
A9: A | B9: 200 | C9: 14000 | D9: 53 a 59,9 g | E9: =IF(SUM(B6:B11)=0,0,B9/SUM(B6:B11)) -> 0.22988506 | F9: =IF(B9=0,0,B9/30*C9) -> 93333.333
A10: B | B10: 50 | C10: 12000 | D10: 46 a 52,9 g | E10: =IF(SUM(B6:B11)=0,0,B10/SUM(B6:B11)) -> 0.057471264 | F10: =IF(B10=0,0,B10/30*C10) -> 20000
A11: C | B11: 20 | C11: 10000 | D11: < 46 g | E11: =IF(SUM(B6:B11)=0,0,B11/SUM(B6:B11)) -> 0.022988506 | F11: =IF(B11=0,0,B11/30*C11) -> 6666.6667
A12: Total de huevos | B12: =SUM(B6:B11) -> 870 | C12: Referencia NTC 1240; verifica la norma vigente
A13: Ingreso total del día | B13: =SUM(F6:F11) -> 455333.33 | C13: ='🏠 Inicio'!B8 -> COP $
A14: Precio promedio por huevo | B14: =IF(B12=0,0,B13/B12) -> 523.37165 | C14: ='🏠 Inicio'!B8 -> COP $
A16: Peso de un huevo en g | B16: 63
A17: Categoría | B17: =IF(B16>=78,"Jumbo",IF(B16>=67,"AAA",IF(B16>=60,"AA",IF(B16>=53,"A",IF(B16>=46,"B","C"))))) -> AA
A20: Calculadora RM · RM Agroinversiones · Cursos online de gallinas ponedoras · WhatsApp +57 322 952 1224

Sheet 🔁 Conversiones
B1: Conversiones | D1: ⟵ Volver al inicio
A2: Convierte medidas comunes de producción. | C2: ="Granja: "&'🏠 Inicio'!B6&" · Moneda: "&'🏠 Inicio'!B8 -> Granja: Mi granja · Moneda: COP $
A4: ✏️ TUS DATOS
A5: Huevos | B5: 870 | C5: huevos → cubetas (30)
A6: Resultado | B6: =B5/30 -> 29
A8: Cubetas | B8: 29 | C8: cubetas → huevos (30)
A9: Resultado | B9: =B8*30 -> 870
A11: Huevos | B11: 870 | C11: huevos → docenas
A12: Resultado | B12: =B11/12 -> 72.5
A14: Kg | B14: 100 | C14: kg → libras (1 libra = 0,5 kg)
A15: Resultado | B15: =B14/0.5 -> 200
A17: Kg | B17: 100 | C17: kg → arrobas (1 arroba = 12,5 kg)
A18: Resultado | B18: =B17/12.5 -> 8
A20: Kg | B20: 115 | C20: kg → bultos de 40 kg
A21: Resultado | B21: =B20/40 -> 2.875
A23: Gramos por gallina al día | B23: 115 | C23: g → kg por cada 1.000 gallinas
A24: Resultado | B24: =B23*1000/1000 -> 115
A27: Calculadora RM · RM Agroinversiones · Cursos online de gallinas ponedoras · WhatsApp +57 322 952 1224

Sheet 🏦 Inversión y retorno
B1: Inversión y retorno | D1: ⟵ Volver al inicio
A2: Calcula inversión inicial y tiempo de recuperación. | C2: ="Granja: "&'🏠 Inicio'!B6&" · Moneda: "&'🏠 Inicio'!B8 -> Granja: Mi granja · Moneda: COP $
A4: ✏️ TUS DATOS
A5: Galpón y adecuaciones | B5: 15000000 | C5: ='🏠 Inicio'!B8 -> COP $
A6: Equipos (comederos, bebederos, nidos) | B6: 4000000 | C6: ='🏠 Inicio'!B8 -> COP $
A7: Pollitas o gallinas | B7: ='🐣 Levante'!B17 -> 22620000 | C7: costo por pollita lista
A8: Capital de trabajo inicial | B8: 3000000 | C8: ='🏠 Inicio'!B8 -> COP $
A9: Ganancia mensual esperada | B9: ='💰 Costos y ganancia'!B20 -> 1773750 | C9: ='🏠 Inicio'!B8 -> COP $
A10: 📊 RESULTADOS
A11: Inversión total | B11: =SUM(B5:B8) -> 44620000 | C11: ='🏠 Inicio'!B8 -> COP $
A12: Meses para recuperar la inversión | B12: =IF(B9<=0,"No se recupera con esta ganancia",B11/B9) -> 25.155743 | C12: meses
A13: Rentabilidad anual sobre la inversión (%) | B13: =IF(B11=0,0,B9*12/B11) -> 0.47702824
A15: Calculadora RM · RM Agroinversiones · Cursos online de gallinas ponedoras · WhatsApp +57 322 952 1224

Sheet 🐔 Gallina de descarte
B1: Gallina de descarte | D1: ⟵ Volver al inicio
A2: Estima el ingreso por venta de gallinas al final del ciclo. | C2: ="Granja: "&'🏠 Inicio'!B6&" · Moneda: "&'🏠 Inicio'!B8 -> Granja: Mi granja · Moneda: COP $
A4: ✏️ TUS DATOS
A5: Gallinas para vender al final | B5: 920 | C5: gallinas
A6: Peso promedio en kg | B6: 1.9 | C6: kg
A7: Precio por kilo en pie | B7: 6500 | C7: ='🏠 Inicio'!B8 -> COP $
A8: 📊 RESULTADOS
A9: Kilos totales | B9: =B5*B6 -> 1748 | C9: kg
A10: Ingreso por descarte | B10: =B9*B7 -> 11362000 | C10: ='🏠 Inicio'!B8 -> COP $
A11: Ingreso por gallina | B11: =IF(B5=0,0,B10/B5) -> 12350 | C11: ='🏠 Inicio'!B8 -> COP $
A13: Calculadora RM · RM Agroinversiones · Cursos online de gallinas ponedoras · WhatsApp +57 322 952 1224
